{
    "SoccerTwos": {
        "elo": 1199.0014391117093,
        "checkpoints": [
            {
                "steps": 3500,
                "file_path": "results\\logtest_1\\SoccerTwos\\SoccerTwos-3500.onnx",
                "reward": 0.0,
                "creation_time": 1736590271.5100703,
                "auxillary_file_paths": [
                    "results\\logtest_1\\SoccerTwos\\SoccerTwos-3500.pt"
                ]
            }
        ],
        "final_checkpoint": {
            "steps": 3500,
            "file_path": "results\\logtest_1\\SoccerTwos.onnx",
            "reward": 0.0,
            "creation_time": 1736590271.5100703,
            "auxillary_file_paths": [
                "results\\logtest_1\\SoccerTwos\\SoccerTwos-3500.pt"
            ]
        }
    },
    "metadata": {
        "stats_format_version": "0.3.0",
        "mlagents_version": "0.28.0",
        "torch_version": "1.10.0+cpu"
    }
}